hyperfast/__init__.py
hyperfast/hyper_network/__init__.py
hyperfast/hyper_network/configuration.py
hyperfast/hyper_network/embedding.py
hyperfast/hyper_network/model.py
hyperfast/hyper_network/network.py
hyperfast/main_network/__init__.py
hyperfast/main_network/configuration.py
hyperfast/main_network/model.py
hyperfast/main_network/network.py
hyperfast/standardize_data/__init__.py
hyperfast/standardize_data/inference.py
hyperfast/standardize_data/training.py
hyperfast/utils/__init__.py
hyperfast/utils/cuda.py
hyperfast/utils/model_downloader.py
hyperfast/utils/seed.py
fast_hyperfast-1.0.3.dist-info/METADATA
fast_hyperfast-1.0.3.dist-info/WHEEL
fast_hyperfast-1.0.3.dist-info/licenses/LICENSE
fast_hyperfast-1.0.3.dist-info/RECORD
