Metadata-Version: 2.4
Name: fast_hyperfast
Version: 1.0.3
Summary: HyperFast (https://github.com/AI-sandbox/HyperFast) but customizable (and in some cases faster too!)
License-File: LICENSE
Requires-Python: >=3.10
Requires-Dist: pandas>=2.2.3
Requires-Dist: pydantic>=2.10.4
Requires-Dist: requests>=2.32.3
Requires-Dist: scikit-learn==1.5.2
Requires-Dist: torch>=2.5.1
Requires-Dist: tqdm>=4.67.1
Requires-Dist: xlrd>=2.0.1
